src/__init__.py
src/conf.py
src/tidy_project_pbxproj.py
src/xcode_helper.py
src/xcode_helper_test.py
src/xcode_helper_v2.py
tidy_project-0.1.dist-info/LICENSE
tidy_project-0.1.dist-info/METADATA
tidy_project-0.1.dist-info/WHEEL
tidy_project-0.1.dist-info/entry_points.txt
tidy_project-0.1.dist-info/top_level.txt
tidy_project-0.1.dist-info/RECORD
