Metadata-Version: 2.1
Name: tidy-project
Version: 0.1
Summary: UNKNOWN
Home-page: https://github.com/colinsarah/tidy_project
Author: colinsarah
Author-email: 
License: UNKNOWN
Platform: UNKNOWN
Classifier: Programming Language :: Python :: 3
Classifier: License :: OSI Approved :: MIT License
Classifier: Operating System :: OS Independent
Requires-Dist: flask (>=1.1.0)
